odoo/addons/project_tag/README.rst
odoo/addons/project_tag/__init__.py
odoo/addons/project_tag/__manifest__.py
odoo/addons/project_tag/i18n/de.po
odoo/addons/project_tag/i18n/es_AR.po
odoo/addons/project_tag/i18n/fr.po
odoo/addons/project_tag/i18n/fr_FR.po
odoo/addons/project_tag/i18n/he.po
odoo/addons/project_tag/i18n/it.po
odoo/addons/project_tag/i18n/project_tag.pot
odoo/addons/project_tag/models/__init__.py
odoo/addons/project_tag/models/project.py
odoo/addons/project_tag/models/project_task.py
odoo/addons/project_tag/readme/CONTRIBUTORS.rst
odoo/addons/project_tag/readme/DESCRIPTION.rst
odoo/addons/project_tag/readme/USAGE.rst
odoo/addons/project_tag/static/description/icon.png
odoo/addons/project_tag/static/description/index.html
odoo/addons/project_tag/views/project.xml
odoo/addons/project_tag/views/project_task.xml
odoo14_addon_project_tag-14.0.1.1.0.dist-info/METADATA
odoo14_addon_project_tag-14.0.1.1.0.dist-info/WHEEL
odoo14_addon_project_tag-14.0.1.1.0.dist-info/top_level.txt
odoo14_addon_project_tag-14.0.1.1.0.dist-info/RECORD
